{
  "recentFiles": [
    {
      "basename": "index",
      "path": "index.md"
    },
    {
      "basename": "Go vs Rust",
      "path": "Inbox/Go vs Rust.md"
    },
    {
      "basename": "Recipe manager",
      "path": "Inbox/Recipe manager.md"
    },
    {
      "basename": "Zettelkasten CLI",
      "path": "Inbox/Zettelkasten CLI.md"
    },
    {
      "basename": "KubeVirt",
      "path": "Notes/KubeVirt.md"
    },
    {
      "basename": "Managing multiple interests",
      "path": "Notes/Managing multiple interests.md"
    },
    {
      "basename": "Pacemaker",
      "path": "Notes/Pacemaker.md"
    },
    {
      "basename": "eBPF",
      "path": "Notes/eBPF.md"
    },
    {
      "basename": "It's not about time, it's about energy",
      "path": "Notes/It's not about time, it's about energy.md"
    }
  ],
  "omittedPaths": [],
  "maxLength": null,
  "openType": "tab"
}